torch_dxdt/__init__.py
torch_dxdt/base.py
torch_dxdt/finite_difference.py
torch_dxdt/kalman.py
torch_dxdt/kernel.py
torch_dxdt/savitzky_golay.py
torch_dxdt/spectral.py
torch_dxdt/spline_method.py
torch_dxdt/whittaker.py
torch_dxdt-0.1.1.dist-info/licenses/LICENSE
torch_dxdt-0.1.1.dist-info/METADATA
torch_dxdt-0.1.1.dist-info/WHEEL
torch_dxdt-0.1.1.dist-info/top_level.txt
torch_dxdt-0.1.1.dist-info/RECORD
