Metadata-Version: 2.4
Name: torch-dxdt
Version: 0.1.1
Summary: Differentiable numerical differentiation for noisy time series in PyTorch
Author-email: Maximilian Stölzle <maximilian@stoelzle.ch>
License: MIT
Project-URL: Homepage, https://github.com/mstoelzle/torch-dxdt
Project-URL: Documentation, https://mstoelzle.github.io/torch-dxdt
Project-URL: Repository, https://github.com/mstoelzle/torch-dxdt
Project-URL: Issues, https://github.com/mstoelzle/torch-dxdt/issues
Keywords: pytorch,differentiation,numerical-differentiation,time-series,deep-learning,automatic-differentiation,signal-processing,kalman-filter,savitzky-golay
Classifier: Development Status :: 3 - Alpha
Classifier: Intended Audience :: Science/Research
Classifier: License :: OSI Approved :: MIT License
Classifier: Operating System :: OS Independent
Classifier: Programming Language :: Python :: 3
Classifier: Programming Language :: Python :: 3.9
Classifier: Programming Language :: Python :: 3.10
Classifier: Programming Language :: Python :: 3.11
Classifier: Programming Language :: Python :: 3.12
Classifier: Programming Language :: Python :: 3.13
Classifier: Topic :: Scientific/Engineering
Classifier: Topic :: Scientific/Engineering :: Mathematics
Classifier: Topic :: Scientific/Engineering :: Artificial Intelligence
Requires-Python: >=3.9
License-File: LICENSE
Requires-Dist: torch>=1.10.0
Requires-Dist: scipy>=1.7.0
Requires-Dist: numpy>=1.20.0
Provides-Extra: test
Requires-Dist: pytest>=6.0; extra == "test"
Requires-Dist: derivative>=0.6.0; extra == "test"
Requires-Dist: matplotlib>=3.0; extra == "test"
Provides-Extra: docs
Requires-Dist: sphinx>=4.0; extra == "docs"
Requires-Dist: sphinx-rtd-theme>=1.0; extra == "docs"
Requires-Dist: sphinx-copybutton>=0.5; extra == "docs"
Requires-Dist: myst-parser>=0.18; extra == "docs"
Requires-Dist: sphinx-autodoc-typehints>=1.18; extra == "docs"
Provides-Extra: dev
Requires-Dist: torch-dxdt[docs,test]; extra == "dev"
Requires-Dist: ruff>=0.1.0; extra == "dev"
Requires-Dist: mypy>=0.9; extra == "dev"
Dynamic: license-file
